openwillis/face/__init__.py
openwillis/face/eye_blink.py
openwillis/face/face_landmark.py
openwillis/face/facial_emotion.py
openwillis/face/head_movement.py
openwillis/face/preprocess_video.py
openwillis/face/config/eye.json
openwillis/face/config/facial.json
openwillis/face/config/preprocess.json
openwillis/face/util/__init__.py
openwillis/face/util/crop_utils.py
openwillis/face/util/speaking_utils.py
openwillis_face-1.1.0.dist-info/METADATA
openwillis_face-1.1.0.dist-info/WHEEL
openwillis_face-1.1.0.dist-info/top_level.txt
openwillis_face-1.1.0.dist-info/RECORD
