Metadata-Version: 2.4
Name: openwillis-face
Version: 1.1.0
Summary: digital health measurement
Home-page: https://github.com/bklynhlth/openwillis
Author: bklynhlth
Author-email: admin@bklynhlth.com
License: Apache
Requires-Python: >=3.9, <3.11
Requires-Dist: tensorflow==2.15.1
Requires-Dist: mediapipe==0.10.18
Requires-Dist: opencv-python==4.10.0.84
Requires-Dist: protobuf==4.25.5
Requires-Dist: pandas==2.2.3
Requires-Dist: protobuf3-to-dict==0.1.5
Requires-Dist: deepface==0.0.93
Requires-Dist: scipy==1.11.4
Requires-Dist: scikit-learn==1.5.2
Requires-Dist: tf-keras==2.15.1
Requires-Dist: py-feat==0.6.2
Requires-Dist: numpy==1.23.5
Dynamic: author
Dynamic: author-email
Dynamic: description-content-type
Dynamic: home-page
Dynamic: license
Dynamic: requires-dist
Dynamic: requires-python
Dynamic: summary
